<?xml version="1.0" encoding="utf-8"?>
<product>
  <projectCode />
  <productNumber>XXX00000000</productNumber>
  <title>Green Eggs and Ham | Book Club by Early Moments</title>
  <ingress>&lt;p&gt;&lt;em&gt;Green Eggs and Ham&lt;/em&gt; is a timeless classic and Dr. Seuss’s most popular book, selling more than 13 million copies since 1960. In this masterpiece &lt;em&gt;Green Eggs and Ham&lt;/em&gt;, Seuss uses only 50 simple words. Children will delight in following persistent Sam-I-Am on his quest to convince a grumpy sourpuss that green eggs and ham are indeed tasty. You and your child will enjoy this book in a house, with a mouse, with a goat, or on a boat. &lt;em&gt;Bon appetite!&lt;/em&gt;&lt;/p&gt;
&lt;p&gt;&lt;strong style="color: #ca2d92;"&gt;Tie-in Activity: Try pausing at the end of a few verses of &lt;em&gt;Green Eggs and Ham&lt;/em&gt; so that your child can finish with the rhyming word. Or celebrate the story by having a “green” meal with your baby. (Peas, anyone?) &lt;/strong&gt;&lt;/p&gt;</ingress>
  <text>&lt;p&gt;&lt;img src="/upload/NextBook/BRU/BRP_GreenEggs_spread.jpg" alt="Green Eggs And Ham Preview" /&gt;&lt;a href="https://orders.earlymoments.com/seuss4for1sbm.aspx?key=4QFM&amp;amp;VendorCode=EMS1" target="_Blank"&gt;&lt;img style="float: right; margin-left: 10px;" src="/upload/EarlyMoments/Art/green_arrow.gif" border="0" alt="" align="bottom" /&gt;&lt;/a&gt;&lt;/p&gt;<format /><visible>false</visible><weight /><available /><priority /><recommendedAge /><url>/Templates/Default/Pages/Article.aspx?id=47678</url><image1>/upload/EarlyMoments/BRP/covers/green_eggs_and_ham.jpg</image1></text>
  <image2 />
  <thumbnail />
  <created>2009-08-12</created>
  <removed />
  <published />
  <ageCategories />
</product>